catkin_pkg/__init__.py
catkin_pkg/changelog.py
catkin_pkg/changelog_generator.py
catkin_pkg/changelog_generator_vcs.py
catkin_pkg/cmake.py
catkin_pkg/condition.py
catkin_pkg/group_dependency.py
catkin_pkg/group_membership.py
catkin_pkg/metapackage.py
catkin_pkg/package.py
catkin_pkg/package_templates.py
catkin_pkg/package_version.py
catkin_pkg/packages.py
catkin_pkg/python_setup.py
catkin_pkg/rospack.py
catkin_pkg/terminal_color.py
catkin_pkg/tool_detection.py
catkin_pkg/topological_order.py
catkin_pkg/workspace_vcs.py
catkin_pkg/workspaces.py
catkin_pkg/cli/__init__.py
catkin_pkg/cli/create_pkg.py
catkin_pkg/cli/find_pkg.py
catkin_pkg/cli/generate_changelog.py
catkin_pkg/cli/package_version.py
catkin_pkg/cli/prepare_release.py
catkin_pkg/cli/tag_changelog.py
catkin_pkg/cli/test_changelog.py
catkin_pkg/templates/CMakeLists.txt.in
catkin_pkg/templates/metapackage.cmake.in
catkin_pkg/templates/package.xml.in
catkin_pkg-1.1.0.dist-info/LICENSE
catkin_pkg-1.1.0.dist-info/METADATA
catkin_pkg-1.1.0.dist-info/WHEEL
catkin_pkg-1.1.0.dist-info/entry_points.txt
catkin_pkg-1.1.0.dist-info/top_level.txt
catkin_pkg-1.1.0.dist-info/RECORD
