Metadata-Version: 2.1
Name: catkin-pkg
Version: 1.1.0
Summary: catkin package library
Home-page: http://wiki.ros.org/catkin_pkg
Author: Dirk Thomas
Author-email: dthomas@osrfoundation.org
Maintainer: ROS Infrastructure Team
License: BSD
Project-URL: Source code, https://github.com/ros-infrastructure/catkin_pkg
Project-URL: Issue tracker, https://github.com/ros-infrastructure/catkin_pkg/issues
Keywords: catkin,ROS
Platform: UNKNOWN
Classifier: Programming Language :: Python
Classifier: License :: OSI Approved :: BSD License
Requires-Python: >=3.6
Provides-Extra: test
License-File: LICENSE
